events_ingestion_client/__init__.py
events_ingestion_client/api_client.py
events_ingestion_client/configuration.py
events_ingestion_client/rest.py
events_ingestion_client/api/__init__.py
events_ingestion_client/api/events_api.py
events_ingestion_client/models/__init__.py
events_ingestion_client/models/all_of_test_gen_test_outcome_integration_component_schema_integrations.py
events_ingestion_client/models/all_of_test_gen_test_outcome_integrations_schema_testgen.py
events_ingestion_client/models/all_of_test_outcome_item_integrations_schema_testgen.py
events_ingestion_client/models/all_of_test_outcome_item_schema_integrations.py
events_ingestion_client/models/all_of_test_outcomes_api_schema_component_integrations.py
events_ingestion_client/models/all_of_testgen_dataset_schema_table_group_configuration.py
events_ingestion_client/models/all_of_testgen_dataset_schema_tables.py
events_ingestion_client/models/dataset_operation_api_schema.py
events_ingestion_client/models/http_error_schema.py
events_ingestion_client/models/message_log_event_api_schema.py
events_ingestion_client/models/metric_log_api_schema.py
events_ingestion_client/models/run_status_api_schema.py
events_ingestion_client/models/test_gen_test_outcome_integration_component_schema.py
events_ingestion_client/models/test_gen_test_outcome_integrations_schema.py
events_ingestion_client/models/test_outcome_item_integrations_schema.py
events_ingestion_client/models/test_outcome_item_schema.py
events_ingestion_client/models/test_outcomes_api_schema.py
events_ingestion_client/models/testgen_dataset_schema.py
events_ingestion_client/models/testgen_item_schema.py
events_ingestion_client/models/testgen_item_test_parameters_schema.py
events_ingestion_client/models/testgen_table_group_v1_schema.py
events_ingestion_client/models/testgen_table_schema.py
test/__init__.py
test/test_all_of_test_gen_test_outcome_integration_component_schema_integrations.py
test/test_all_of_test_gen_test_outcome_integrations_schema_testgen.py
events_ingestion_client-1.5.0.dist-info/METADATA
events_ingestion_client-1.5.0.dist-info/WHEEL
events_ingestion_client-1.5.0.dist-info/top_level.txt
events_ingestion_client-1.5.0.dist-info/RECORD
