Metadata-Version: 2.1
Name: events-ingestion-client
Version: 1.5.0
Summary: Event Ingestion API
Home-page: UNKNOWN
Author-email: support@datakitchen.io
License: UNKNOWN
Keywords: Swagger,Event Ingestion API
Platform: UNKNOWN
Requires-Dist: urllib3 (>=1.15)
Requires-Dist: six (>=1.10)
Requires-Dist: certifi
Requires-Dist: python-dateutil
